setup.py
rehowdoi/__init__.py
rehowdoi/rehowdoi.py
rehowdoi.egg-info/PKG-INFO
rehowdoi.egg-info/SOURCES.txt
rehowdoi.egg-info/dependency_links.txt
rehowdoi.egg-info/entry_points.txt
rehowdoi.egg-info/requires.txt
rehowdoi.egg-info/top_level.txt