Metadata-Version: 1.0
Name: rehowdoi
Version: 1.0.9
Summary: A code search tool
Home-page: UNKNOWN
Author: UNKNOWN
Author-email: UNKNOWN
License: UNKNOWN
Platform: UNKNOWN
